manila_tempest_tests/__init__.py
manila_tempest_tests/clients.py
manila_tempest_tests/config.py
manila_tempest_tests/plugin.py
manila_tempest_tests/share_exceptions.py
manila_tempest_tests/utils.py
manila_tempest_tests/common/__init__.py
manila_tempest_tests/common/constants.py
manila_tempest_tests/common/remote_client.py
manila_tempest_tests/common/waiters.py
manila_tempest_tests/services/__init__.py
manila_tempest_tests/services/share/__init__.py
manila_tempest_tests/services/share/json/__init__.py
manila_tempest_tests/services/share/json/shares_client.py
manila_tempest_tests/services/share/v2/__init__.py
manila_tempest_tests/services/share/v2/json/__init__.py
manila_tempest_tests/services/share/v2/json/shares_client.py
manila_tempest_tests/tests/__init__.py
manila_tempest_tests/tests/api/__init__.py
manila_tempest_tests/tests/api/base.py
manila_tempest_tests/tests/api/test_access_rules_metadata.py
manila_tempest_tests/tests/api/test_access_rules_metadata_negative.py
manila_tempest_tests/tests/api/test_availability_zones.py
manila_tempest_tests/tests/api/test_availability_zones_negative.py
manila_tempest_tests/tests/api/test_backup.py
manila_tempest_tests/tests/api/test_backup_negative.py
manila_tempest_tests/tests/api/test_extensions.py
manila_tempest_tests/tests/api/test_limits.py
manila_tempest_tests/tests/api/test_metadata.py
manila_tempest_tests/tests/api/test_metadata_negative.py
manila_tempest_tests/tests/api/test_microversions.py
manila_tempest_tests/tests/api/test_public_shares.py
manila_tempest_tests/tests/api/test_public_shares_negative.py
manila_tempest_tests/tests/api/test_quotas.py
manila_tempest_tests/tests/api/test_quotas_negative.py
manila_tempest_tests/tests/api/test_replication.py
manila_tempest_tests/tests/api/test_replication_export_locations.py
manila_tempest_tests/tests/api/test_replication_export_locations_negative.py
manila_tempest_tests/tests/api/test_replication_negative.py
manila_tempest_tests/tests/api/test_replication_snapshots.py
manila_tempest_plugin-2.9.0.dist-info/AUTHORS
manila_tempest_plugin-2.9.0.dist-info/LICENSE
manila_tempest_plugin-2.9.0.dist-info/METADATA
manila_tempest_plugin-2.9.0.dist-info/WHEEL
manila_tempest_plugin-2.9.0.dist-info/entry_points.txt
manila_tempest_plugin-2.9.0.dist-info/pbr.json
manila_tempest_plugin-2.9.0.dist-info/top_level.txt
manila_tempest_plugin-2.9.0.dist-info/RECORD
