Metadata-Version: 2.1
Name: manila-tempest-plugin
Version: 2.9.0
Summary: Tempest plugin manila-tempest-plugin
Home-page: https://docs.openstack.org/manila/latest/
Author: OpenStack
Author-email: openstack-discuss@lists.openstack.org
Classifier: Environment :: OpenStack
Classifier: Intended Audience :: Information Technology
Classifier: Intended Audience :: System Administrators
Classifier: License :: OSI Approved :: Apache Software License
Classifier: Operating System :: POSIX :: Linux
Classifier: Programming Language :: Python
Classifier: Programming Language :: Python :: 3
Classifier: Programming Language :: Python :: 3.9
Classifier: Programming Language :: Python :: 3.10
Classifier: Programming Language :: Python :: 3.11
Classifier: Programming Language :: Python :: 3.12
Requires-Python: >=3.9
License-File: LICENSE
License-File: AUTHORS
Requires-Dist: pbr >=3.0.0
Requires-Dist: ddt >=1.6.0
Requires-Dist: oslo.log >=3.36.0
Requires-Dist: tempest >=31.1.0
